AUTHORS.rst
CHANGES.rst
LICENSE.txt
MANIFEST.in
README.rst
setup.py
django_reset/__init__.py
django_reset/models.py
django_reset.egg-info/PKG-INFO
django_reset.egg-info/SOURCES.txt
django_reset.egg-info/dependency_links.txt
django_reset.egg-info/not-zip-safe
django_reset.egg-info/top_level.txt
django_reset/management/__init__.py
django_reset/management/sql.py
django_reset/management/commands/__init__.py
django_reset/management/commands/reset.py
django_reset/management/commands/sqlreset.py